simulator/__init__.py
simulator/dryer.py
simulator/util.py
vzug/__init__.py
vzug/basic_device.py
vzug/const.py
vzug/digest_auth.py
vzug/dryer.py
vzug/washing_machine.py
vzug_api-0.1.1.dist-info/LICENSE
vzug_api-0.1.1.dist-info/METADATA
vzug_api-0.1.1.dist-info/WHEEL
vzug_api-0.1.1.dist-info/top_level.txt
vzug_api-0.1.1.dist-info/RECORD
