Metadata-Version: 2.1
Name: vzug-api
Version: 0.1.1
Summary: Unofficial python API for V-ZUG devices
Home-page: https://github.com/mico-micic/vzug-api
Author: Mićo Mićić
Author-email: mico@micic.ch
License: GNU General Public License v3.0
Platform: UNKNOWN
Classifier: Development Status :: 3 - Alpha
Classifier: Environment :: Console
Classifier: Intended Audience :: Developers
Classifier: License :: OSI Approved :: GNU General Public License v3 or later (GPLv3+)
Classifier: Operating System :: POSIX :: Linux
Classifier: Operating System :: MacOS :: MacOS X
Classifier: Operating System :: Microsoft :: Windows
Classifier: Programming Language :: Python :: 3.9
Classifier: Programming Language :: Python :: 3.8
Classifier: Topic :: Home Automation
License-File: LICENSE
Requires-Dist: aiohttp (>=3.8.0)
Requires-Dist: tenacity (>=8.0.0)
Requires-Dist: yarl (>=1.7.0)
